pathhelper/__init__.py
pathhelper/pathhelper.py
pathhelper-0.1.0.dist-info/licenses/LICENSE
pathhelper-0.1.0.dist-info/METADATA
pathhelper-0.1.0.dist-info/WHEEL
pathhelper-0.1.0.dist-info/top_level.txt
pathhelper-0.1.0.dist-info/RECORD
