Metadata-Version: 2.4
Name: pathhelper
Version: 0.1.0
Summary: Lightweight helpers for working with filesystem paths.
Author: SleepyJack
License-Expression: MIT
Project-URL: Homepage, https://github.com/SleepyJack/pathhelper
Project-URL: Source, https://github.com/SleepyJack/pathhelper
Project-URL: Tracker, https://github.com/SleepyJack/pathhelper/issues
Project-URL: Documentation, https://github.com/SleepyJack/pathhelper#readme
Keywords: filesystem,path,directory,file,utilities
Classifier: Development Status :: 3 - Alpha
Classifier: Intended Audience :: Developers
Classifier: Operating System :: OS Independent
Classifier: Programming Language :: Python :: 3
Requires-Python: >=3.7
License-File: LICENSE
Dynamic: license-file
